Python_ARQ/__init__.py
Python_ARQ/arq.py
python_arq-6.0.7.dist-info/LICENSE
python_arq-6.0.7.dist-info/METADATA
python_arq-6.0.7.dist-info/WHEEL
python_arq-6.0.7.dist-info/top_level.txt
python_arq-6.0.7.dist-info/RECORD
