Metadata-Version: 2.1
Name: python_arq
Version: 6.0.7
Summary: Asynchronous Python Wrapper For A.R.Q API.
Home-page: https://github.com/thehamkercat/Python_ARQ
Author: TheHamkerCat
Author-email: thehamkercat@gmail.com
License: MIT
Keywords: API,ARQ_API,Python-ARQ,ARQ,A.R.Q
Classifier: Development Status :: 5 - Production/Stable
Classifier: Intended Audience :: Developers
Classifier: License :: OSI Approved :: MIT License
Classifier: Programming Language :: Python :: 3.8
Classifier: Programming Language :: Python :: 3.9
License-File: LICENSE
Requires-Dist: pyrogram
Requires-Dist: dotmap
Requires-Dist: aiohttp
Requires-Dist: aiofiles
